hassdevice/__init__.py
hassdevice/devices.py
hassdevice/devices.py~
hassdevice/hosts.py
hassdevice/hosts.py~
hassdevice-0.1.4.dist-info/DESCRIPTION.rst
hassdevice-0.1.4.dist-info/METADATA
hassdevice-0.1.4.dist-info/RECORD
hassdevice-0.1.4.dist-info/WHEEL
hassdevice-0.1.4.dist-info/metadata.json
hassdevice-0.1.4.dist-info/top_level.txt
